<?xml version="1.0" encoding="UTF-8" standalone="no"?>
<livraisons>
<livraison livreurId="0" id="932576342" latitude="45.737278" longitude="4.8754654"/>
<livraison livreurId="0" id="190866533" latitude="45.777367" longitude="4.879716"/>
<livraison livreurId="0" id="3020993750" latitude="45.779194" longitude="4.84137"/>
<livraison livreurId="0" id="21674895" latitude="45.769028" longitude="4.847287"/>
<livraison livreurId="0" id="26296856" latitude="45.769527" longitude="4.868148"/>
<livraison livreurId="0" id="388568803" latitude="45.746437" longitude="4.885732"/>
<livraison livreurId="0" id="1349383079" latitude="45.731087" longitude="4.9053183"/>
<livraison livreurId="0" id="25173835" latitude="45.75045" longitude="4.8569613"/>
<livraison livreurId="0" id="21604550" latitude="45.7609" longitude="4.8455243"/>
<livraison livreurId="0" id="25327124" latitude="45.771343" longitude="4.8509526"/>
<livraison livreurId="0" id="26149152" latitude="45.75098" longitude="4.8930354"/>
<livraison livreurId="0" id="25452887" latitude="45.731243" longitude="4.838523"/>
<livraison livreurId="0" id="25450962" latitude="45.750816" longitude="4.844156"/>
<livraison livreurId="0" id="1242371158" latitude="45.76781" longitude="4.888736"/>
<livraison livreurId="0" id="1288817934" latitude="45.749992" longitude="4.8702283"/>
<livraison livreurId="0" id="25316190" latitude="45.77171" longitude="4.843264"/>
<livraison livreurId="0" id="54695781" latitude="45.7698" longitude="4.8779163"/>
<livraison livreurId="0" id="26086126" latitude="45.75925" longitude="4.865438"/>
<livraison livreurId="0" id="60685056" latitude="45.77473" longitude="4.8740892"/>
<livraison livreurId="0" id="3113108906" latitude="45.75934" longitude="4.854254"/>
<livraison livreurId="0" id="190951242" latitude="45.77006" longitude="4.898899"/>
<livraison livreurId="0" id="25327152" latitude="45.767445" longitude="4.8517523"/>
<livraison livreurId="0" id="48830471" latitude="45.757717" longitude="4.876506"/>
<livraison livreurId="0" id="26132218" latitude="45.730568" longitude="4.864488"/>
<livraison livreurId="0" id="26084603" latitude="45.744072" longitude="4.8383346"/>
<livraison livreurId="0" id="27362904" latitude="45.731186" longitude="4.8797636"/>
<livraison livreurId="0" id="1794342477" latitude="45.73425" longitude="4.8503695"/>
<livraison livreurId="0" id="26106487" latitude="45.764225" longitude="4.8342485"/>
<livraison livreurId="0" id="60901983" latitude="45.734013" longitude="4.897888"/>
</livraisons>
